encrypted_secrets/__init__.py
encrypted_secrets/apps.py
encrypted_secrets/conf.py
encrypted_secrets/tests.py
encrypted_secrets/util.py
encrypted_secrets/crypto/__init__.py
encrypted_secrets/crypto/aes.py
encrypted_secrets/management/__init__.py
encrypted_secrets/management/commands/__init__.py
encrypted_secrets/management/commands/edit_secrets.py
encrypted_secrets/management/commands/init_secrets.py
encrypted_secrets/management/commands/show_secrets.py
django_encrypted_secrets-0.9.5.dist-info/LICENSE.txt
django_encrypted_secrets-0.9.5.dist-info/METADATA
django_encrypted_secrets-0.9.5.dist-info/WHEEL
django_encrypted_secrets-0.9.5.dist-info/top_level.txt
django_encrypted_secrets-0.9.5.dist-info/RECORD
