Metadata-Version: 2.1
Name: django-encrypted-secrets
Version: 0.9.5
Summary: A Django app for managing secrets.
Home-page: https://github.com/nzaillian/django-encrypted-secrets
Author: Axiomatic LLC
Author-email: contact@axiomatic.im
License: MIT License
Platform: UNKNOWN
Classifier: Environment :: Web Environment
Classifier: Framework :: Django
Classifier: Framework :: Django :: 2.0
Classifier: Framework :: Django :: 2.1
Classifier: Intended Audience :: Developers
Classifier: License :: OSI Approved :: MIT License
Classifier: Operating System :: OS Independent
Classifier: Operating System :: OS Independent
Classifier: Programming Language :: Python
Classifier: Programming Language :: Python :: 3
Classifier: Programming Language :: Python :: 3.5
Classifier: Programming Language :: Python :: 3.6
Classifier: Programming Language :: Python :: 3.7
Classifier: Programming Language :: Python :: 3 :: Only
Requires-Dist: PyCrypto
Requires-Dist: PyYAML
